_wlplan.cpython-310-x86_64-linux-gnu.so
_wlplan/__init__.pyi
_wlplan/data.pyi
_wlplan/feature_generator.pyi
_wlplan/graph_generator.pyi
_wlplan/planning.pyi
_wlplan/py.typed
wlplan/__init__.py
wlplan/__version__.py
wlplan/data.py
wlplan/feature_generator.py
wlplan/graph_generator.py
wlplan/planning.py
wlplan-2.1.0.dist-info/METADATA
wlplan-2.1.0.dist-info/WHEEL
wlplan-2.1.0.dist-info/top_level.txt
wlplan-2.1.0.dist-info/RECORD
wlplan-2.1.0.dist-info/licenses/LICENSE
