Metadata-Version: 2.4
Name: wlplan
Version: 2.1.0
Summary: WLPlan: Relational Features for PDDL Planning
Author: Dillon Z. Chen
Author-email: "Dillon Z. Chen" <dillon.chen1@gmail.com>
License: MIT License
Project-URL: Homepage, https://dillonzchen.github.io/comingsoon.html
Project-URL: Documentation, https://dillonzchen.github.io/comingsoon.html
Project-URL: Source, https://github.com/dillonzchen/wlplan
Keywords: wlplan,automated planning,machine learning
Classifier: Intended Audience :: Developers
Classifier: Intended Audience :: Education
Classifier: Intended Audience :: Science/Research
Classifier: Topic :: Scientific/Engineering
Classifier: Topic :: Scientific/Engineering :: Mathematics
Classifier: Topic :: Scientific/Engineering :: Artificial Intelligence
Classifier: Topic :: Software Development
Classifier: Topic :: Software Development :: Libraries
Classifier: Topic :: Software Development :: Libraries :: Python Modules
Classifier: Programming Language :: C++
Classifier: Programming Language :: Python :: 3
Requires-Python: >=3.10
License-File: LICENSE
Requires-Dist: networkx
Requires-Dist: pddl==0.4.1
Requires-Dist: python-sat==1.8.dev14
Dynamic: author
Dynamic: classifier
Dynamic: description
Dynamic: description-content-type
Dynamic: keywords
Dynamic: license
Dynamic: license-file
Dynamic: requires-dist
Dynamic: requires-python
